[
    {
        "Incident": "Dixie Fire (CA)",
        "Type": "Wildfire",
        "State": "California, USA",
        "Size": "963309 Acres",
        "Updated": "11/1/2021",
        "href": "/incident/7690/"
    },
    {
        "Incident": "North Complex",
        "Type": "Wildfire",
        "State": "California, USA",
        "Size": "318935 Acres",
        "Updated": "11/5/2021",
        "href": "/incident/6997/"
    },
    {
        "Incident": "Monument Fire",
        "Type": "Wildfire",
        "State": "California, USA",
        "Size": "223124 Acres",
        "Updated": "11/1/2021",
        "href": "/incident/7750/"
    },
    {
        "Incident": "Caldor Fire",
        "Type": "Wildfire",
        "State": "California, USA",
        "Size": "221835 Acres",
        "Updated": "11/17/2021",
        "href": "/incident/7801/"
    },
    {
        "Incident": "Schneider Springs BAER",
        "Type": "Burned Area Emergency Response",
        "State": "Washington, USA",
        "Size": "107322 Acres",
        "Updated": "12/3/2021",
        "href": "/incident/7860/"
    },
    {
        "Incident": "Windy Fire",
        "Type": "Wildfire",
        "State": "California, USA",
        "Size": "97528 Acres",
        "Updated": "12/14/2021",
        "href": "/incident/7841/"
    },
    {
        "Incident": "KNP Complex ",
        "Type": "Wildfire",
        "State": "California, USA",
        "Size": "88307 Acres",
        "Updated": "12/21/2021",
        "href": "/incident/7838/"
    },
    {
        "Incident": "Cub Creek 2 Fire",
        "Type": "Wildfire",
        "State": "Washington, USA",
        "Size": "70186 Acres",
        "Updated": "12/1/2021",
        "href": "/incident/7675/"
    },
    {
        "Incident": "Cedar Creek",
        "Type": "Wildfire",
        "State": "Washington, USA",
        "Size": "55572 Acres",
        "Updated": "12/1/2021",
        "href": "/incident/7655/"
    },
    {
        "Incident": "Twentyfive Mile BAER",
        "Type": "Burned Area Emergency Response",
        "State": "Washington, USA",
        "Size": "22117 Acres",
        "Updated": "12/3/2021",
        "href": "/incident/7846/"
    },
    {
        "Incident": "Alisal Fire",
        "Type": "Wildfire",
        "State": "California, USA",
        "Size": "16970 Acres",
        "Updated": "11/20/2021",
        "href": "/incident/7862/"
    },
    {
        "Incident": "Dry Cabin",
        "Type": "Wildfire",
        "State": "Montana, USA",
        "Size": "3735 Acres",
        "Updated": "11/22/2021",
        "href": "/incident/7660/"
    },
    {
        "Incident": "Fall 2021 Bastrop County Prescribed Burn",
        "Type": "Prescribed Fire",
        "State": "Texas, USA",
        "Size": "2800 Acres",
        "Updated": "4 days ago",
        "href": "/incident/7867/"
    },
    {
        "Incident": "Luccah Fire",
        "Type": "Wildfire",
        "State": "Texas, USA",
        "Size": "2000 Acres",
        "Updated": "1:10 hrs. ago",
        "href": "/incident/7939/"
    },
    {
        "Incident": "Kaibab NF South Zone Rx Fire",
        "Type": "Prescribed Fire",
        "State": "Arizona, USA",
        "Size": "1100 Acres",
        "Updated": "1/3/2022",
        "href": "/incident/5922/"
    },
    {
        "Incident": "Rolling Pines Fire",
        "Type": "Wildfire",
        "State": "Texas, USA",
        "Size": "812 Acres",
        "Updated": "1 day ago",
        "href": "/incident/7927/"
    },
    {
        "Incident": "Pacheco Canyon Prescribed Pile Burn",
        "Type": "Prescribed Fire",
        "State": "New Mexico, USA",
        "Size": "443 Acres",
        "Updated": "1/13/2022",
        "href": "/incident/7921/"
    },
    {
        "Incident": "Baney Unit 3C RX Fire - Magdalena RD",
        "Type": "Prescribed Fire",
        "State": "New Mexico, USA",
        "Size": "291 Acres",
        "Updated": "1 day ago",
        "href": "/incident/7883/"
    },
    {
        "Incident": "KRRD Prescribed Fire 2021/22",
        "Type": "Prescribed Fire",
        "State": "California, USA",
        "Size": "200 Acres",
        "Updated": "12/15/2021",
        "href": "/incident/7891/"
    },
    {
        "Incident": "Cordovas Prescribed Pile Burn",
        "Type": "Prescribed Fire",
        "State": "New Mexico, USA",
        "Size": "157 Acres",
        "Updated": "1/14/2022",
        "href": "/incident/7918/"
    },
    {
        "Incident": "Valley RX Burns",
        "Type": "Prescribed Fire",
        "State": "California, USA",
        "Size": "53 Acres",
        "Updated": "11/3/2021",
        "href": "/incident/7871/"
    },
    {
        "Incident": "WG Jones State Forest Pres. Fire 2022",
        "Type": "Prescribed Fire",
        "State": "Texas, USA",
        "Size": "0 Acres",
        "Updated": "7 hrs. ago",
        "href": "/incident/7938/"
    },
    {
        "Incident": "Brodbeck-Hooper GLO Prescribed Fires '22",
        "Type": "Prescribed Fire",
        "State": "Texas, USA",
        "Size": "0 Acres",
        "Updated": "8 hrs. ago",
        "href": "/incident/7937/"
    },
    {
        "Incident": "McMillian Prescribed Fires 2022",
        "Type": "Prescribed Fire",
        "State": "Texas, USA",
        "Size": "0 Acres",
        "Updated": "9 hrs. ago",
        "href": "/incident/7931/"
    },
    {
        "Incident": "SHSU University Camp Prescribed Fire '22",
        "Type": "Prescribed Fire",
        "State": "Texas, USA",
        "Size": "0 Acres",
        "Updated": "9 hrs. ago",
        "href": "/incident/7932/"
    },
    {
        "Incident": "Davey Dogwood Park Prescribed Fires 2022",
        "Type": "Prescribed Fire",
        "State": "Texas, USA",
        "Size": "0 Acres",
        "Updated": "9 hrs. ago",
        "href": "/incident/7933/"
    },
    {
        "Incident": "Fairchild State Forest Pres. Fires 2022",
        "Type": "Prescribed Fire",
        "State": "Texas, USA",
        "Size": "0 Acres",
        "Updated": "9 hrs. ago",
        "href": "/incident/7935/"
    },
    {
        "Incident": "Kirby State Forest Prescribed Fires 2022",
        "Type": "Prescribed Fire",
        "State": "Texas, USA",
        "Size": "0 Acres",
        "Updated": "9 hrs. ago",
        "href": "/incident/7930/"
    },
    {
        "Incident": "Leona GLO Prescribed Fires 2022",
        "Type": "Prescribed Fire",
        "State": "Texas, USA",
        "Size": "0 Acres",
        "Updated": "9 hrs. ago",
        "href": "/incident/7936/"
    },
    {
        "Incident": "Lake Naconiche Prescribed Fires 2022",
        "Type": "Prescribed Fire",
        "State": "Texas, USA",
        "Size": "0 Acres",
        "Updated": "1 day ago",
        "href": "/incident/7934/"
    },
    {
        "Incident": "Huron-Manistee NFs '22 Winter Rx Burning",
        "Type": "Prescribed Fire",
        "State": "Michigan, USA",
        "Size": "0 Acres",
        "Updated": "2 days ago",
        "href": "/incident/7928/"
    },
    {
        "Incident": "2022 Humboldt-Toiyabe Prescribed Fire",
        "Type": "Prescribed Fire",
        "State": "Nevada, USA",
        "Size": "0 Acres",
        "Updated": "2 days ago",
        "href": "/incident/7310/"
    },
    {
        "Incident": "San Juan NF Prescribed Fire Program",
        "Type": "Prescribed Fire",
        "State": "Colorado, USA",
        "Size": "0 Acres",
        "Updated": "1/19/2022",
        "href": "/incident/6288/"
    },
    {
        "Incident": "Southwest District BLM Prescribed Fire ",
        "Type": "Prescribed Fire",
        "State": "Colorado, USA",
        "Size": "0 Acres",
        "Updated": "1/13/2022",
        "href": "/incident/7852/"
    },
    {
        "Incident": "Slash Pile Burning 2021",
        "Type": "Prescribed Fire",
        "State": "Colorado, USA",
        "Size": "0 Acres",
        "Updated": "1/13/2022",
        "href": "/incident/4648/"
    },
    {
        "Incident": "Dixie Post-Fire BAER",
        "Type": "Burned Area Emergency Response",
        "State": "California, USA",
        "Size": "0 Acres",
        "Updated": "12/23/2021",
        "href": "/incident/7811/"
    },
    {
        "Incident": "East Troublesome Post-Fire BAER",
        "Type": "Burned Area Emergency Response",
        "State": "Colorado, USA",
        "Size": "0 Acres",
        "Updated": "12/6/2021",
        "href": "/incident/7267/"
    },
    {
        "Incident": "Cub Creek 2 BAER",
        "Type": "Burned Area Emergency Response",
        "State": "Washington, USA",
        "Size": "0 Acres",
        "Updated": "12/3/2021",
        "href": "/incident/7830/"
    },
    {
        "Incident": "Cedar Creek BAER",
        "Type": "Burned Area Emergency Response",
        "State": "Washington, USA",
        "Size": "0 Acres",
        "Updated": "12/3/2021",
        "href": "/incident/7832/"
    },
    {
        "Incident": "Prescribed Fire Projects 2021",
        "Type": "Prescribed Fire",
        "State": "Oregon, USA",
        "Size": "0 Acres",
        "Updated": "12/1/2021",
        "href": "/incident/7426/"
    },
    {
        "Incident": "Pleasant Valley Prescribed Burn",
        "Type": "Prescribed Fire",
        "State": "Arizona, USA",
        "Size": "0 Acres",
        "Updated": "11/22/2021",
        "href": "/incident/7896/"
    },
    {
        "Incident": "Klamath NF Fall/Winter '21 Rx Burning",
        "Type": "Prescribed Fire",
        "State": "California, USA",
        "Size": "0 Acres",
        "Updated": "11/18/2021",
        "href": "/incident/7889/"
    },
    {
        "Incident": "Alisal Post-Fire BAER",
        "Type": "Burned Area Emergency Response",
        "State": "California, USA",
        "Size": "0 Acres",
        "Updated": "11/15/2021",
        "href": "/incident/7873/"
    },
    {
        "Incident": "Hoosier National Forest Prescribed Fire ",
        "Type": "Prescribed Fire",
        "State": "Indiana, USA",
        "Size": "0 Acres",
        "Updated": "11/12/2021",
        "href": "/incident/7887/"
    },
    {
        "Incident": "McCash Post-Fire BAER",
        "Type": "Burned Area Emergency Response",
        "State": "California, USA",
        "Size": "0 Acres",
        "Updated": "11/5/2021",
        "href": "/incident/7870/"
    },
    {
        "Incident": "River Complex Post-Fire BAER",
        "Type": "Burned Area Emergency Response",
        "State": "California, USA",
        "Size": "0 Acres",
        "Updated": "11/5/2021",
        "href": "/incident/7868/"
    }
]